acomod/MainWindow.py
acomod/MainWindow.ui
acomod/__init__.py
acomod/global_settings.py
acomod/matplotlibWidget.py
acomod/preferences.py
acomod/preferences.ui
acomod/recordSignal.py
acomod/resources.py
acomod/sonidist.py
acomod-0.1.8.dist-info/LICENSE
acomod-0.1.8.dist-info/METADATA
acomod-0.1.8.dist-info/WHEEL
acomod-0.1.8.dist-info/eager_resources.txt
acomod-0.1.8.dist-info/entry_points.txt
acomod-0.1.8.dist-info/top_level.txt
acomod-0.1.8.dist-info/RECORD
