Metadata-Version: 2.1
Name: acomod
Version: 0.1.8
Summary: Acoustic Oscillations Viewer
Home-page: https://github.com/bslew/acomod
Author: Bartosz Lew
Author-email: bartosz.lew@protonmail.com
License: UNKNOWN
Platform: UNKNOWN
Classifier: Development Status :: 3 - Alpha
Classifier: Topic :: Utilities
Classifier: License :: OSI Approved :: BSD License
Requires-Dist: PyQt5 (>=5.0)
Requires-Dist: numpy (>=1.16)
Requires-Dist: matplotlib (>=3.0)
Requires-Dist: sounddevice
Requires-Dist: soundfile
Requires-Dist: scipy (>=1.2)
